fennec_asr/__init__.py
fennec_asr/_version.py
fennec_asr/cli.py
fennec_asr/client.py
fennec_asr/exceptions.py
fennec_asr/main.py
fennec_asr/mic.py
fennec_asr/py.typed
fennec_asr/shortcuts.py
fennec_asr/streaming.py
fennec_asr/types.py
fennec_asr/utils.py
fennec_asr-1.1.4.dist-info/licenses/LICENSE
fennec_asr-1.1.4.dist-info/METADATA
fennec_asr-1.1.4.dist-info/WHEEL
fennec_asr-1.1.4.dist-info/entry_points.txt
fennec_asr-1.1.4.dist-info/top_level.txt
fennec_asr-1.1.4.dist-info/RECORD
