Metadata-Version: 2.4
Name: fennec-asr
Version: 1.1.4
Summary: Python SDK for the Fennec ASR API
Author-email: Your Team <info@fennec-asr.com>
License: MIT
Project-URL: Homepage, https://github.com/Fennec-ASR/fennec-asr-sdk
Project-URL: Issues, https://github.com/Fennec-ASR/fennec-asr-sdk/issues
Classifier: Programming Language :: Python :: 3
Classifier: Programming Language :: Python :: 3 :: Only
Classifier: Programming Language :: Python :: 3.9
Classifier: License :: OSI Approved :: MIT License
Classifier: Operating System :: OS Independent
Classifier: Typing :: Typed
Requires-Python: >=3.9
License-File: LICENSE
Requires-Dist: requests<3,>=2.31.0
Requires-Dist: websockets<16,>=12
Requires-Dist: typing-extensions>=4.8.0
Provides-Extra: mic
Requires-Dist: sounddevice>=0.4.7; extra == "mic"
Requires-Dist: numpy>=1.22.0; extra == "mic"
Dynamic: license-file
